LICENSE
README.md
setup.py
TIME/__init__.py
TIME/core.py
TIME/example.py
TIME/utils.py
TIME_python.egg-info/PKG-INFO
TIME_python.egg-info/SOURCES.txt
TIME_python.egg-info/dependency_links.txt
TIME_python.egg-info/requires.txt
TIME_python.egg-info/top_level.txt